manhelp/__init__.py
manhelp/main.py
manhelp/search.py
manhelp-0.1.34.dist-info/METADATA
manhelp-0.1.34.dist-info/WHEEL
manhelp-0.1.34.dist-info/entry_points.txt
manhelp-0.1.34.dist-info/top_level.txt
manhelp-0.1.34.dist-info/RECORD
