Metadata-Version: 2.1
Name: manhelp
Version: 0.1.34
Summary: manhelp provides an intuitive interface for finding Linux commands. It uses natural language processing to understand human language queries and returns the most relevant Linux commands. Ideal for both beginners who are learning Linux and experienced users who need a quick reference.
Author-email: me <example@email.com>
License: MIT
Requires-Python: >=3.8
Requires-Dist: sentence-transformers ==2.7.0
Requires-Dist: typer ==0.12.3
